.coveragerc
.gitignore
LICENSE
MANIFEST.in
README.md
VERSION.txt
classifiers.txt
requirements.txt
setup.py
.github/workflows/main.yaml
doc/Makefile
doc/conf.py
doc/index.rst
doc/make.bat
doc/toolboxes.rst
doc/auto_examples/auto_examples_jupyter.zip
doc/auto_examples/auto_examples_python.zip
doc/auto_examples/index.rst
doc/auto_examples/geostat/plot_gridsearch.ipynb
doc/auto_examples/geostat/plot_gridsearch.py
doc/auto_examples/geostat/plot_gridsearch.py.md5
doc/auto_examples/geostat/plot_gridsearch.rst
doc/auto_examples/geostat/plot_gridsearch_codeobj.pickle
doc/auto_examples/geostat/plot_ordinary_kriging.ipynb
doc/auto_examples/geostat/plot_ordinary_kriging.py
doc/auto_examples/geostat/plot_ordinary_kriging.py.md5
doc/auto_examples/geostat/plot_ordinary_kriging.rst
doc/auto_examples/geostat/plot_ordinary_kriging_codeobj.pickle
doc/auto_examples/geostat/plot_variogram.ipynb
doc/auto_examples/geostat/plot_variogram.py
doc/auto_examples/geostat/plot_variogram.py.md5
doc/auto_examples/geostat/plot_variogram.rst
doc/auto_examples/geostat/plot_variogram_codeobj.pickle
doc/auto_examples/geostat/sg_execution_times.rst
doc/auto_examples/geostat/images/sphx_glr_plot_gridsearch_001.html
doc/auto_examples/geostat/images/sphx_glr_plot_gridsearch_001.png
doc/auto_examples/geostat/images/sphx_glr_plot_ordinary_kriging_001.html
doc/auto_examples/geostat/images/sphx_glr_plot_ordinary_kriging_001.png
doc/auto_examples/geostat/images/sphx_glr_plot_variogram_001.html
doc/auto_examples/geostat/images/sphx_glr_plot_variogram_001.png
doc/auto_examples/geostat/images/sphx_glr_plot_variogram_002.html
doc/auto_examples/geostat/images/sphx_glr_plot_variogram_002.png
doc/auto_examples/geostat/images/thumb/sphx_glr_plot_gridsearch_thumb.png
doc/auto_examples/geostat/images/thumb/sphx_glr_plot_ordinary_kriging_thumb.png
doc/auto_examples/geostat/images/thumb/sphx_glr_plot_variogram_thumb.png
doc/gen_modules/hydrobox.geostat.ext_drift_kriging.rst
doc/gen_modules/hydrobox.geostat.gridsearch.rst
hydrobox.egg-info/PKG-INFO
hydrobox.egg-info/SOURCES.txt
hydrobox.egg-info/dependency_links.txt
hydrobox.egg-info/not-zip-safe
hydrobox.egg-info/requires.txt
hydrobox.egg-info/top_level.txt
