Metadata-Version: 1.1
Name: hydrobox
Version: 0.2.0
Summary: Hydrological toolbox build on top of scipy and pandas
Home-page: UNKNOWN
Author: Mirko Maelicke
Author-email: mirko.maelicke@kit.edu
License: MIT
Platform: UNKNOWN
Classifier: Development Status :: 4 - Beta
Classifier: Intended Audience :: Science/Research
Classifier: License :: OSI Approved :: MIT License
Classifier: Natural Language :: English
Classifier: Programming Language :: Python :: 3.4
Classifier: Programming Language :: Python :: 3.5
Classifier: Programming Language :: Python :: 3.6
Classifier: Topic :: Scientific/Engineering :: Information Analysis
